powerline_dice/__init__.py
powerline_dice/dice.py
powerline_dice-1.0.0.dist-info/LICENSE
powerline_dice-1.0.0.dist-info/METADATA
powerline_dice-1.0.0.dist-info/WHEEL
powerline_dice-1.0.0.dist-info/top_level.txt
powerline_dice-1.0.0.dist-info/RECORD
